cryptosenti/__init__.py
cryptosenti/client.py
cryptosenti/config.py
cryptosenti/models.py
cryptosenti-0.1.0.dist-info/METADATA
cryptosenti-0.1.0.dist-info/WHEEL
cryptosenti-0.1.0.dist-info/licenses/LICENSE
cryptosenti-0.1.0.dist-info/RECORD
