Metadata-Version: 2.4
Name: cryptosenti
Version: 0.1.0
Summary: Python client for PySenti crypto sentiment analysis SignalR API
Project-URL: Homepage, https://github.com/AndMu/PySenti.Api
Project-URL: Repository, https://github.com/AndMu/PySenti.Api
Project-URL: Bug Tracker, https://github.com/AndMu/PySenti.Api/issues
Author-email: PySenti <info@pysenti.lt>
License:                     GNU GENERAL PUBLIC LICENSE
License-File: LICENSE
Keywords: analysis,cryptocurrency,sentiment,signalr,trading
Classifier: Development Status :: 3 - Alpha
Classifier: Intended Audience :: Developers
Classifier: Intended Audience :: Financial and Insurance Industry
Classifier: License :: OSI Approved :: GNU General Public License v3 (GPLv3)
Classifier: Programming Language :: Python :: 3
Classifier: Programming Language :: Python :: 3.10
Classifier: Programming Language :: Python :: 3.11
Classifier: Programming Language :: Python :: 3.12
Classifier: Topic :: Office/Business :: Financial
Classifier: Topic :: Software Development :: Libraries :: Python Modules
Requires-Python: >=3.10
Requires-Dist: aiohttp>=3.8.0
Requires-Dist: pydantic>=2.0.0
Requires-Dist: pysignalr>=1.0.0
Requires-Dist: python-dateutil>=2.8.0
Provides-Extra: dev
Requires-Dist: black>=23.0.0; extra == 'dev'
Requires-Dist: mypy>=1.5.0; extra == 'dev'
Requires-Dist: pre-commit>=3.0.0; extra == 'dev'
Requires-Dist: pytest-asyncio>=0.21.0; extra == 'dev'
Requires-Dist: pytest-cov>=4.0.0; extra == 'dev'
Requires-Dist: pytest>=7.0.0; extra == 'dev'
Requires-Dist: ruff>=0.1.0; extra == 'dev'
Provides-Extra: examples
Requires-Dist: asyncio-mqtt>=0.13.0; extra == 'examples'
